<?xml version="1.0" encoding="UTF-8"?>

<document id="DDI-DrugBank.d746"> 
   <sentence id="DDI-DrugBank.d746.s0" text="ARAMINE should be used with caution in digitalized patients, since the combination of digitalis and sympathomimetic amines may cause ectopic arrhythmias. " new_text="ARAMINE@@should@@be@@used@@with@@caution@@in@@digitalized@@patients@@,@@since@@the@@combination@@of@@digitalis@@and@@sympathomimetic amines@@may@@cause@@ectopic@@arrhythmias@@.@@"> 
      <entity id="DDI-DrugBank.d746.s0.e0" charOffset="0-6" type="brand" text="ARAMINE" position="0"/>  
      <entity id="DDI-DrugBank.d746.s0.e1" charOffset="86-94" type="group" text="digitalis" position="14"/>  
      <entity id="DDI-DrugBank.d746.s0.e2" charOffset="100-121" type="group" text="sympathomimetic amines" position="16"/>  
      <pair id="DDI-DrugBank.d746.s0.p0" e1="DDI-DrugBank.d746.s0.e0" e2="DDI-DrugBank.d746.s0.e1" ddi="false" flags="True" e1_name="ARAMINE" e2_name="digitalis" e1_pos="0" e2_pos="14" path="0@@3@@18@@12@@14@@">ARAMINE@@@@nsubjpass@@used@@advcl@@cause@@nsubj@@combination@@prep_of@@digitalis</pair>  
      <pair id="DDI-DrugBank.d746.s0.p1" e1="DDI-DrugBank.d746.s0.e0" e2="DDI-DrugBank.d746.s0.e2" ddi="false" flags="True" e1_name="ARAMINE" e2_name="sympathomimetic amines" e1_pos="0" e2_pos="16" path="0@@3@@18@@12@@16@@">ARAMINE@@@@nsubjpass@@used@@advcl@@cause@@nsubj@@combination@@prep_of@@sympathomimetic amines</pair>  
      <pair id="DDI-DrugBank.d746.s0.p2" e1="DDI-DrugBank.d746.s0.e1" e2="DDI-DrugBank.d746.s0.e2" ddi="true" type="effect" flags="True" e1_name="digitalis" e2_name="sympathomimetic amines" e1_pos="14" e2_pos="16" path="14@@16@@">digitalis@@@@conj_and@@sympathomimetic amines</pair> 
   </sentence>  
   <sentence id="DDI-DrugBank.d746.s1" text="Monoamine oxidase inhibitors or tricyclic antidepressants may potentiate the action of sympathomimetic amines. " new_text="Monoamine oxidase inhibitors@@or@@tricyclic antidepressants@@may@@potentiate@@the@@action@@of@@sympathomimetic amines@@.@@"> 
      <entity id="DDI-DrugBank.d746.s1.e0" charOffset="0-27" type="group" text="Monoamine oxidase inhibitors" position="0"/>  
      <entity id="DDI-DrugBank.d746.s1.e1" charOffset="32-56" type="group" text="tricyclic antidepressants" position="2"/>  
      <entity id="DDI-DrugBank.d746.s1.e2" charOffset="87-108" type="group" text="sympathomimetic amines" position="8"/>  
      <pair id="DDI-DrugBank.d746.s1.p0" e1="DDI-DrugBank.d746.s1.e0" e2="DDI-DrugBank.d746.s1.e1" ddi="false" flags="True" e1_name="Monoamine oxidase inhibitors" e2_name="tricyclic antidepressants" e1_pos="0" e2_pos="2" path="0@@2@@">Monoamine oxidase inhibitors@@@@conj_or@@tricyclic antidepressants</pair>  
      <pair id="DDI-DrugBank.d746.s1.p1" e1="DDI-DrugBank.d746.s1.e0" e2="DDI-DrugBank.d746.s1.e2" ddi="true" type="effect" flags="True" e1_name="Monoamine oxidase inhibitors" e2_name="sympathomimetic amines" e1_pos="0" e2_pos="8" path="0@@4@@6@@8@@">Monoamine oxidase inhibitors@@@@nsubj@@potentiate@@dobj@@action@@prep_of@@sympathomimetic amines</pair>  
      <pair id="DDI-DrugBank.d746.s1.p2" e1="DDI-DrugBank.d746.s1.e1" e2="DDI-DrugBank.d746.s1.e2" ddi="true" type="effect" flags="True" e1_name="tricyclic antidepressants" e2_name="sympathomimetic amines" e1_pos="2" e2_pos="8" path="2@@4@@6@@8@@">tricyclic antidepressants@@@@nsubj@@potentiate@@dobj@@action@@prep_of@@sympathomimetic amines</pair> 
   </sentence>  
   <sentence id="DDI-DrugBank.d746.s2" text="Therefore, when initiating pressor therapy in patients receiving these drugs, the initial dose should be small and given with caution." new_text="Therefore@@,@@when@@initiating@@pressor@@therapy@@in@@patients@@receiving@@these@@drugs@@,@@the@@initial@@dose@@should@@be@@small@@and@@given@@with@@caution@@.@@"/> 
</document>
